pdftokenizer/__about__.py
pdftokenizer/__init__.py
pdftokenizer/types.py
pdftokenizer/utils.py
pdftokenizer/extractors/__init__.py
pdftokenizer/extractors/base.py
pdftokenizer/extractors/pdfplumber.py
pdftokenizer/extractors/tesseract.py
pdftokenizer-0.0.4.dist-info/METADATA
pdftokenizer-0.0.4.dist-info/WHEEL
pdftokenizer-0.0.4.dist-info/licenses/LICENSE.txt
pdftokenizer-0.0.4.dist-info/RECORD
