Metadata-Version: 2.4
Name: pdftokenizer
Version: 0.0.4
Summary: Tool to extract PAWLs tokens from PDFs
Project-URL: Documentation, https://github.com/JSv4/pdftokenizer#readme
Project-URL: Issues, https://github.com/JSv4/pdftokenizer/issues
Project-URL: Source, https://github.com/JSv4/pdftokenizer
Author-email: JSv4 <scrudato@umich.edu>
License-Expression: MIT
License-File: LICENSE.txt
Classifier: Development Status :: 4 - Beta
Classifier: Programming Language :: Python
Classifier: Programming Language :: Python :: 3.10
Classifier: Programming Language :: Python :: 3.11
Classifier: Programming Language :: Python :: 3.12
Classifier: Programming Language :: Python :: Implementation :: CPython
Classifier: Programming Language :: Python :: Implementation :: PyPy
Requires-Python: >=3.10
Requires-Dist: pdf2image>=1.17.0
Requires-Dist: pdfplumber>=0.11.0
Requires-Dist: plasmapdf==0.1.2
Requires-Dist: pypdf
Requires-Dist: pytesseract>=0.3.0
